hubmap_template_helper/__init__.py
hubmap_template_helper/compatibility.py
hubmap_template_helper/uuids.py
hubmap_template_helper-0.0.2.dist-info/LICENSE
hubmap_template_helper-0.0.2.dist-info/METADATA
hubmap_template_helper-0.0.2.dist-info/WHEEL
hubmap_template_helper-0.0.2.dist-info/top_level.txt
hubmap_template_helper-0.0.2.dist-info/RECORD
