Metadata-Version: 2.1
Name: hubmap_template_helper
Version: 0.0.2
Summary: Helper functions for templates within HuBMAP Data Portal
Author-email: "Thomas C. Smits" <tsmits@hms.harvard.edu>
Project-URL: Homepage, https://github.com/thomcsmits/hubmap_template_helper
Project-URL: Bug Tracker, https://github.com/thomcsmits/hubmap_template_helper/issues
Keywords: HuBMAP
Classifier: Programming Language :: Python :: 3
Classifier: License :: OSI Approved :: MIT License
Classifier: Operating System :: OS Independent
Requires-Python: >=3.0
License-File: LICENSE
Requires-Dist: requests >=0.2.0
Requires-Dist: pandas >=0.20.0
